Metadata-Version: 1.1
Name: retirable-resources
Version: 0.1.8
Summary: Retirable resources for Firestore.
Home-page: https://github.com/SteveAlexander/retirable_resources
Author: Steve Alexander
Author-email: steve@stevea.com
License: MIT
Download-URL: https://github.com/SteveAlexander/retirable_resources/archive/refs/tags/0.1.8.tar.gz
Platform: UNKNOWN
Classifier: Development Status :: 4 - Beta
Classifier: Intended Audience :: Developers
Classifier: License :: OSI Approved :: MIT License
Classifier: Programming Language :: Python :: 3.9
